<?xml version="1.0" encoding="UTF-8"?>
<proj><name>AZ0020010</name><package>com.nec.jp.orteus.metamorBase.AZ0020</package><jndi>com_nec_jp_orteus_metamorBase_AZ0020</jndi><ctrls><comment></comment><ctrl><name>AZ0020010</name><status>active</status><BaseClass>Servlet</BaseClass><define></define><WizType>0</WizType><mets><comment></comment><method><name>initialEvent</name><jname>初期処理</jname><description></description><BaseMethod>onClick</BaseMethod><define></define><event-type>none</event-type><event-options><comment></comment></event-options><args><comment>引数設定情報</comment><arg><name>arg 1</name><jname>ボタン名 (日本語、省略可)</jname><datatype>String</datatype><in>0</in><ismed>0</ismed><param>初期処理</param></arg><arg><name>arg 2</name><jname>ボタンＩＤ (必須)</jname><datatype>String</datatype><in>0</in><ismed>0</ismed><param>initialEvent</param></arg><arg><name>arg 3</name><jname>移動先JSP (省略可)</jname><datatype>String</datatype><in>0</in><ismed>0</ismed><param></param></arg></args><cells><comment>mediator情報</comment><arg><name>arg 1</name><datatype>String</datatype><in>out</in><ismed>1</ismed><param>h_USER_CD</param><format></format></arg><arg><name>arg 2</name><datatype>String</datatype><in>out</in><ismed>1</ismed><param>USER_CD</param><format></format></arg></cells><entities><comment>エンティティ情報</comment><entity><description></description></entity></entities></method><method><name>select</name><jname>読込</jname><description></description><BaseMethod>onClick</BaseMethod><define></define><event-type>select</event-type><event-options><comment></comment></event-options><args><comment>引数設定情報</comment><arg><name>arg 1</name><jname>ボタン名 (日本語、省略可)</jname><datatype>String</datatype><in>0</in><ismed>0</ismed><param>読込</param></arg><arg><name>arg 2</name><jname>ボタンＩＤ (必須)</jname><datatype>String</datatype><in>0</in><ismed>0</ismed><param>select</param></arg><arg><name>arg 3</name><jname>移動先JSP (省略可)</jname><datatype>String</datatype><in>0</in><ismed>0</ismed><param></param></arg></args><cells><comment>mediator情報</comment><arg><name>arg 1</name><datatype>String</datatype><in>out</in><ismed>1</ismed><param>h_USER_CD</param><format></format></arg><arg><name>arg 2</name><datatype>String</datatype><in>out</in><ismed>1</ismed><param>USER_CD</param><format></format></arg></cells><entities><comment>エンティティ情報</comment><entity><description></description></entity></entities></method><method><name>update</name><jname>選択解除</jname><description></description><BaseMethod>onClick</BaseMethod><define></define><event-type>update</event-type><event-options><comment></comment></event-options><args><comment>引数設定情報</comment><arg><name>arg 1</name><jname>ボタン名 (日本語、省略可)</jname><datatype>String</datatype><in>0</in><ismed>0</ismed><param>選択解除</param></arg><arg><name>arg 2</name><jname>ボタンＩＤ (必須)</jname><datatype>String</datatype><in>0</in><ismed>0</ismed><param>update</param></arg><arg><name>arg 3</name><jname>移動先JSP (省略可)</jname><datatype>String</datatype><in>0</in><ismed>0</ismed><param></param></arg></args><cells><comment>mediator情報</comment><arg><name>arg 1</name><datatype>String</datatype><in>out</in><ismed>1</ismed><param>h_USER_CD</param><format></format></arg><arg><name>arg 2</name><datatype>String</datatype><in>out</in><ismed>1</ismed><param>USER_CD</param><format></format></arg></cells><entities><comment>エンティティ情報</comment><entity><description></description></entity></entities></method><method><name>clear</name><jname>クリア</jname><description></description><BaseMethod>onClick</BaseMethod><define></define><event-type>none</event-type><event-options><comment></comment></event-options><args><comment>引数設定情報</comment><arg><name>arg 1</name><jname>ボタン名 (日本語、省略可)</jname><datatype>String</datatype><in>0</in><ismed>0</ismed><param>クリア</param></arg><arg><name>arg 2</name><jname>ボタンＩＤ (必須)</jname><datatype>String</datatype><in>0</in><ismed>0</ismed><param>clear</param></arg><arg><name>arg 3</name><jname>移動先JSP (省略可)</jname><datatype>String</datatype><in>0</in><ismed>0</ismed><param></param></arg></args><cells><comment>mediator情報</comment><arg><name>arg 1</name><datatype>String</datatype><in>out</in><ismed>1</ismed><param>h_USER_CD</param><format></format></arg><arg><name>arg 2</name><datatype>String</datatype><in>out</in><ismed>1</ismed><param>USER_CD</param><format></format></arg></cells><entities><comment>エンティティ情報</comment><entity><description></description></entity></entities></method><method><name>close</name><BaseMethod>onClick</BaseMethod><define></define><event-type></event-type><event-options><comment></comment></event-options><args><comment>引数設定情報</comment><arg><name>arg 1</name><jname>ボタン名 (日本語、省略可)</jname><datatype>String</datatype><in>0</in><ismed>0</ismed><param>閉じる</param></arg><arg><name>arg 2</name><jname>ボタンＩＤ (必須)</jname><datatype>String</datatype><in>0</in><ismed>0</ismed><param>close</param></arg><arg><name>arg 3</name><jname>移動先JSP (省略可)</jname><datatype>String</datatype><in>0</in><ismed>0</ismed><param></param></arg></args><cells><comment>mediator情報</comment><arg><name>arg 1</name><datatype>String</datatype><in>out</in><ismed>1</ismed><param>h_USER_CD</param><format></format></arg><arg><name>arg 2</name><datatype>String</datatype><in>out</in><ismed>1</ismed><param>USER_CD</param><format></format></arg></cells><entities><comment>エンティティ情報</comment><entity><description></description></entity></entities></method></mets></ctrl></ctrls><entities><comment></comment><entity><name>select</name><BaseClass>dbms_dynamic_sql</BaseClass><define></define><create><enable>false</enable><status>inactive</status></create><check><enable>true</enable><status>active</status><name>select</name><BaseClass>dbms</BaseClass><WizType>2</WizType><define></define><params><dsn>orteus</dsn><user>orteus</user><password>orteus</password><JDBC>sun.jdbc.odbc.JdbcOdbcDriver</JDBC><jdbc_prefix>jdbc:odbc:</jdbc_prefix><useTransaction>false</useTransaction><sqlcmd>"select "
+"  '現仕様では業務元選択がないため 上記', "
+"  'メソッドwhereのMODE_FORM_FROM_NAMEは', "
+"  '効きません' "
+"from "
+"  dual"</sqlcmd></params><props><comment></comment><property><name>現仕様では業務元選択がないため 上記</name><no>1</no><datatype>CHAR</datatype><inout>out</inout><phrase>select</phrase><tablename></tablename><columnname></columnname><med><cell><name>USER_CD</name><type>in</type><datatype>String</datatype></cell></med></property><property><name>メソッドWHEREのMODE_FORM_FROM_NAMEは</name><no>2</no><datatype>CHAR</datatype><inout>out</inout><phrase>select</phrase><tablename></tablename><columnname></columnname><med><cell><name>USER_CD</name><type>in</type><datatype>String</datatype></cell></med></property><property><name>効きません</name><no>3</no><datatype>CHAR</datatype><inout>out</inout><phrase>select</phrase><tablename></tablename><columnname></columnname><med><cell><name>USER_CD</name><type>in</type><datatype>String</datatype></cell></med></property></props></check><read><enable>true</enable><status>active</status><name>select</name><BaseClass>dbms_dynamic_sql</BaseClass><WizType>2</WizType><define></define><params><dsn>orteus</dsn><user>ORTEUS</user><password>ORTEUS</password><JDBC>oracle.jdbc.driver.OracleDriver</JDBC><jdbc_prefix>jdbc:oracle:thin:@localhost:1521:</jdbc_prefix><useTransaction>true</useTransaction><sqlcmd>"select "
+"  SYS_LOCK_STATUS.\\"CANCEL_CD\\" as \\"CANCEL_CD\\", "
+"  TO_CHAR(SYS_LOCK_STATUS.\\"CREATED_DATE\\", 'YYYY/MM/DD HH24:MI:SS') as \\"CREATED_DATE\\", "
+"  USER_MST.\\"USER_NAME\\" as \\"USER_NAME\\", "
+"  SYS_LOCK_STATUS.\\"MODE_FORM_FROM_NAME\\" as \\"MODE_FORM_FROM_NAME\\", "
+"  SYS_LOCK_STATUS.\\"PLANT_CD\\" as \\"PLANT_CD\\", "
+"  M_PLANT.\\"PLANT_NAME\\" as \\"PLANT_NAME\\", "
+"  SYS_LOCK_STATUS.\\"MODE_FORM_TO_NAME\\" as \\"MODE_FORM_TO_NAME\\" "
+"from "
+"  SYS_LOCK_STATUS, "
+"  USER_MST, "
+"  M_PLANT "
+"where "
+"  SYS_LOCK_STATUS.USER_CD = USER_MST.USER_CD(+) "
+"  and SYS_LOCK_STATUS.PLANT_CD = M_PLANT.PLANT_CD(+) "
+"  and SYS_LOCK_STATUS.\\"MODE_FORM_FROM_NAME\\" = ? "
+"  and SYS_LOCK_STATUS.\\"USER_CD\\" = ? "
+"order by "
+"  SYS_LOCK_STATUS.\\"CREATED_DATE\\", "
+"  SYS_LOCK_STATUS.\\"CANCEL_CD\\", "
+"  M_PLANT.\\"PLANT_CD\\", "
+"  SYS_LOCK_STATUS.\\"MODE_FORM_TO_NAME\\""</sqlcmd></params><props><comment></comment><property><name>CANCEL_CD</name><no>1</no><datatype>DECIMAL</datatype><inout>out</inout><phrase>select</phrase><tablename>SYS_LOCK_STATUS</tablename><columnname>CANCEL_CD</columnname><med><cell><name>CANCEL_CD</name><type>in</type><datatype>String</datatype></cell></med></property><property><name>CREATED_DATE</name><no>2</no><datatype>VARCHAR2</datatype><inout>out</inout><phrase>select</phrase><tablename>SYS_LOCK_STATUS</tablename><columnname>CREATED_DATE</columnname><med><cell><name>CREATE_DATE</name><type>in</type><datatype>String</datatype></cell></med></property><property><name>USER_NAME</name><no>3</no><datatype>VARCHAR2</datatype><inout>out</inout><phrase>select</phrase><tablename>USER_MST</tablename><columnname>USER_NAME</columnname><med><cell><name>USER_NAME</name><type>in</type><datatype>String</datatype></cell></med></property><property><name>MODE_FORM_FROM_NAME</name><no>4</no><datatype>VARCHAR2</datatype><inout>out</inout><phrase>select</phrase><tablename>SYS_LOCK_STATUS</tablename><columnname>MODE_FORM_FROM_NAME</columnname><med><cell><name>MODE_FORM_FROM_NAME</name><type>in</type><datatype>String</datatype></cell></med></property><property><name>PLANT_CD</name><no>5</no><datatype>VARCHAR2</datatype><inout>out</inout><phrase>select</phrase><tablename>SYS_LOCK_STATUS</tablename><columnname>PLANT_CD</columnname><med><cell><name>PLANT_CD</name><type>in</type><datatype>String</datatype></cell></med></property><property><name>PLANT_NAME</name><no>6</no><datatype>VARCHAR2</datatype><inout>out</inout><phrase>select</phrase><tablename>M_PLANT</tablename><columnname>PLANT_NAME</columnname><med><cell><name>PLANT_NAME</name><type>in</type><datatype>String</datatype></cell></med></property><property><name>MODE_FORM_TO_NAME</name><no>7</no><datatype>VARCHAR2</datatype><inout>out</inout><phrase>select</phrase><tablename>SYS_LOCK_STATUS</tablename><columnname>MODE_FORM_TO_NAME</columnname><med><cell><name>MODE_FORM_TO_NAME</name><type>in</type><datatype>String</datatype></cell></med></property><property><name>IN7</name><no>1</no><datatype>VARCHAR2</datatype><inout>in</inout><phrase>where</phrase><tablename>SYS_LOCK_STATUS</tablename><columnname>MODE_FORM_FROM_NAME</columnname><med><cell><name>MODE_FORM_FROM_NAME</name><type>out</type><datatype>String</datatype></cell></med></property><property><name>IN8</name><no>2</no><datatype>VARCHAR2</datatype><inout>in</inout><phrase>where</phrase><tablename>SYS_LOCK_STATUS</tablename><columnname>USER_CD</columnname><med><cell><name>USER_CD</name><type>out</type><datatype>String</datatype></cell></med></property></props></read><update><enable>false</enable><status>inactive</status></update><delete><enable>false</enable><status>inactive</status></delete><call><enable>false</enable><status>inactive</status></call></entity><entity><name>selectTO_NAME</name><BaseClass>dbms_dynamic_sql</BaseClass><define></define><create><enable>false</enable><status>inactive</status></create><check><enable>true</enable><status>active</status><name>selectTO_NAME</name><BaseClass>dbms</BaseClass><WizType>2</WizType><define></define><params><dsn>orteus</dsn><user>orteus</user><password>orteus</password><JDBC>sun.jdbc.odbc.JdbcOdbcDriver</JDBC><jdbc_prefix>jdbc:odbc:</jdbc_prefix><useTransaction>false</useTransaction><sqlcmd>"select "
+"  '現仕様では業務先選択がないため', "
+"  '上記メソッドは使用していません' "
+"from "
+"  dual"</sqlcmd></params><props><comment></comment><property><name>現仕様では業務先選択がないため</name><no>1</no><datatype>CHAR</datatype><inout>out</inout><phrase>select</phrase><tablename></tablename><columnname></columnname><med><cell><name>USER_CD</name><type>in</type><datatype>String</datatype></cell></med></property><property><name>上記メソッドは使用していません</name><no>2</no><datatype>CHAR</datatype><inout>out</inout><phrase>select</phrase><tablename></tablename><columnname></columnname><med><cell><name>USER_CD</name><type>in</type><datatype>String</datatype></cell></med></property></props></check><read><enable>true</enable><status>active</status><name>selectTO_NAME</name><BaseClass>dbms_dynamic_sql</BaseClass><WizType>2</WizType><define></define><params><dsn>orteus</dsn><user>ORTEUS</user><password>ORTEUS</password><JDBC>oracle.jdbc.driver.OracleDriver</JDBC><jdbc_prefix>jdbc:oracle:thin:@localhost:1521:</jdbc_prefix><useTransaction>true</useTransaction><sqlcmd>"select "
+"  SYS_LOCK_STATUS.\\"CANCEL_CD\\" as \\"CANCEL_CD\\", "
+"  TO_CHAR(SYS_LOCK_STATUS.\\"CREATED_DATE\\", 'YYYY/MM/DD HH24:MI:SS') as \\"CREATED_DATE\\", "
+"  USER_MST.\\"USER_NAME\\" as \\"USER_NAME\\", "
+"  SYS_LOCK_STATUS.\\"MODE_FORM_FROM_NAME\\" as \\"MODE_FORM_FROM_NAME\\", "
+"  M_PLANT.\\"PLANT_NAME\\" as \\"PLANT_NAME\\", "
+"  SYS_LOCK_STATUS.\\"MODE_FORM_TO_NAME\\" as \\"MODE_FORM_TO_NAME\\" "
+"from "
+"  SYS_LOCK_STATUS, "
+"  USER_MST, "
+"  M_PLANT "
+"where "
+"  SYS_LOCK_STATUS.USER_CD = USER_MST.USER_CD(+) "
+"  and SYS_LOCK_STATUS.PLANT_CD = M_PLANT.PLANT_CD(+) "
+"  and SYS_LOCK_STATUS.CANCEL_CD IN ( "
+"    select "
+"      CANCEL_CD "
+"    from "
+"      SYS_LOCK_STATUS "
+"    where "
+"      MODE_FORM_TO_NAME = ? "
+"  ) "
+"  and SYS_LOCK_STATUS.\\"USER_CD\\" = ? "
+"order by "
+"  SYS_LOCK_STATUS.\\"CREATED_DATE\\", "
+"  SYS_LOCK_STATUS.\\"CANCEL_CD\\", "
+"  M_PLANT.\\"PLANT_CD\\", "
+"  SYS_LOCK_STATUS.\\"MODE_FORM_TO_NAME\\""</sqlcmd></params><props><comment></comment><property><name>CANCEL_CD</name><no>1</no><datatype>DECIMAL</datatype><inout>out</inout><phrase>select</phrase><tablename>SYS_LOCK_STATUS</tablename><columnname>CANCEL_CD</columnname><med><cell><name>CANCEL_CD</name><type>in</type><datatype>String</datatype></cell></med></property><property><name>CREATED_DATE</name><no>2</no><datatype>VARCHAR2</datatype><inout>out</inout><phrase>select</phrase><tablename>SYS_LOCK_STATUS</tablename><columnname>CREATED_DATE</columnname><med><cell><name>CREATE_DATE</name><type>in</type><datatype>String</datatype></cell></med></property><property><name>USER_NAME</name><no>3</no><datatype>VARCHAR2</datatype><inout>out</inout><phrase>select</phrase><tablename>USER_MST</tablename><columnname>USER_NAME</columnname><med><cell><name>USER_NAME</name><type>in</type><datatype>String</datatype></cell></med></property><property><name>MODE_FORM_FROM_NAME</name><no>4</no><datatype>VARCHAR2</datatype><inout>out</inout><phrase>select</phrase><tablename>SYS_LOCK_STATUS</tablename><columnname>MODE_FORM_FROM_NAME</columnname><med><cell><name>MODE_FORM_FROM_NAME</name><type>in</type><datatype>String</datatype></cell></med></property><property><name>PLANT_NAME</name><no>5</no><datatype>VARCHAR2</datatype><inout>out</inout><phrase>select</phrase><tablename>M_PLANT</tablename><columnname>PLANT_NAME</columnname><med><cell><name>PLANT_NAME</name><type>in</type><datatype>String</datatype></cell></med></property><property><name>MODE_FORM_TO_NAME</name><no>6</no><datatype>VARCHAR2</datatype><inout>out</inout><phrase>select</phrase><tablename>SYS_LOCK_STATUS</tablename><columnname>MODE_FORM_TO_NAME</columnname><med><cell><name>MODE_FORM_TO_NAME</name><type>in</type><datatype>String</datatype></cell></med></property><property><name>IN6</name><no>1</no><datatype>VARCHAR2</datatype><inout>in</inout><phrase>where</phrase><tablename>SYS_LOCK_STATUS</tablename><columnname>MODE_FORM_TO_NAME</columnname><med><cell><name>MODE_FORM_TO_NAME</name><type>out</type><datatype>String</datatype></cell></med></property><property><name>IN7</name><no>2</no><datatype>VARCHAR2</datatype><inout>in</inout><phrase>where</phrase><tablename>SYS_LOCK_STATUS</tablename><columnname>USER_CD</columnname><med><cell><name>USER_CD</name><type>out</type><datatype>String</datatype></cell></med></property></props></read><update><enable>false</enable><status>inactive</status></update><delete><enable>false</enable><status>inactive</status></delete><call><enable>false</enable><status>inactive</status></call></entity></entities><med><comment></comment><cell><name>h_USER_CD</name><datatype>String</datatype><kind>UI</kind><description></description></cell><cell><name>FROM_BUSINESS_NAME</name><datatype>String</datatype><kind>USER</kind><description></description></cell><cell><name>TO_BUSINESS_NAME</name><datatype>String</datatype><kind>USER</kind><description></description></cell><cell><name>LIST_PLANT_NAME</name><datatype>String</datatype><kind>USER</kind><description></description></cell><cell><name>LIST_TO_BUSINESS_NAME</name><datatype>String</datatype><kind>USER</kind><description></description></cell><cell><name>DELETE_FLG</name><datatype>String</datatype><kind>USER</kind><description></description></cell><cell><name>MODE_FORM_FROM_NAME</name><datatype>String</datatype><kind>USER</kind><description>現状未使用(常にnull)。ロック元業務指定で読み込む場合設定する。</description></cell><cell><name>MODE_FORM_TO_NAME</name><datatype>String</datatype><kind>USER</kind><description>現状未使用(常にnull)。ロック先業務指定で読み込む場合設定する。</description></cell><cell><name>PLANT_CD</name><datatype>String</datatype><kind>USER</kind><description></description></cell><cell><name>CANCEL_CD</name><datatype>String</datatype><kind>USER</kind><description></description></cell><cell><name>CREATE_DATE</name><datatype>String</datatype><kind>USER</kind><description></description></cell><cell><name>USER_NAME</name><datatype>String</datatype><kind>USER</kind><description></description></cell><cell><name>PLANT_NAME</name><datatype>String</datatype><kind>USER</kind><description></description></cell><cell><name>USER_CD</name><datatype>String</datatype><kind>UI</kind><description></description></cell></med></proj>
